pyboolean/__init__.py
pyboolean/pyboolean.py
pyboolean-0.1.post4.dist-info/LICENSE
pyboolean-0.1.post4.dist-info/METADATA
pyboolean-0.1.post4.dist-info/WHEEL
pyboolean-0.1.post4.dist-info/top_level.txt
pyboolean-0.1.post4.dist-info/RECORD
